[
  {
    "destKey": "userID",
    "sourceKeys": "userIdOnly",
    "sourceFromGenericMap": true,
    "required": true
  },
  {
    "destKey": "email",
    "sourceKeys": ["traits.email", "context.traits.email", "properties.email"],
    "sourceFromGenericMap": false,
    "required": false
  },
  {
    "destKey": "name",
    "sourceKeys": "name",
    "sourceFromGenericMap": true,
    "required": true
  },
  {
    "destKey": "created",
    "sourceKeys": "timestamp",
    "sourceFromGenericMap": true,
    "required": false
  },
  {
    "destKey": "avatarURL",
    "sourceKeys": "avatar",
    "sourceFromGenericMap": true,
    "required": false
  },
  {
    "destKey": "companies",
    "sourceKeys": ["traits.companies", "context.traits.companies"],
    "sourceFromGenericMap": false,
    "required": false
  },
  {
    "destKey": "customFields",
    "sourceKeys": "traits",
    "sourceFromGenericMap": true,
    "required": false,
    "metadata": {
      "excludes": [
        "name",
        "email",
        "avatar",
        "avatarURL",
        "avatar_URL",
        "companies"
      ]
    }
  }
]
